{
  "project_info": {
    "project_number": "854865861013",
    "firebase_url": "https://link-sdk.firebaseio.com",
    "project_id": "link-sdk",
    "storage_bucket": "link-sdk.appspot.com"
  },
  "client": [
    {
      "client_info": {
        "mobilesdk_app_id": "1:854865861013:android:9a302403a961a545f97e9c",
        "android_client_info": {
          "package_name": "com.example.myawesomeapp"
        }
      },
      "oauth_client": [
        {
          "client_id": "854865861013-c9vvmnnho07lmpokq4eqoevrjkm65j32.apps.googleusercontent.com",
          "client_type": 1,
          "android_info": {
            "package_name": "com.example.myawesomeapp",
            "certificate_hash": "564f29ebeffd514305fb8a3f673b650bcb6dabe9"
          }
        },
        {
          "client_id": "854865861013-as04qpfc2r78ntdd3hg23bqnviufkomd.apps.googleusercontent.com",
          "client_type": 3
        }
      ],
      "api_key": [
        {
          "current_key": "AIzaSyCmLFTmCTPybqj5ttVpvDkkwcLDoPcwuI0"
        }
      ],
      "services": {
        "appinvite_service": {
          "other_platform_oauth_client": [
            {
              "client_id": "854865861013-as04qpfc2r78ntdd3hg23bqnviufkomd.apps.googleusercontent.com",
              "client_type": 3
            },
            {
              "client_id": "854865861013-p42of19a4gqslmocm7dv483uqkqgu1fu.apps.googleusercontent.com",
              "client_type": 2,
              "ios_info": {
                "bundle_id": "com.getmoneytree.sdk.MyAwesomeApp"
              }
            }
          ]
        }
      }
    },
    {
      "client_info": {
        "mobilesdk_app_id": "1:854865861013:android:fa4d1c397a0e79dcf97e9c",
        "android_client_info": {
          "package_name": "com.getmoneytree.sample.awesomeapp"
        }
      },
      "oauth_client": [
        {
          "client_id": "854865861013-2enn4h264b31j0viiv851adp88oppv28.apps.googleusercontent.com",
          "client_type": 1,
          "android_info": {
            "package_name": "com.getmoneytree.sample.awesomeapp",
            "certificate_hash": "564f29ebeffd514305fb8a3f673b650bcb6dabe9"
          }
        },
        {
          "client_id": "854865861013-as04qpfc2r78ntdd3hg23bqnviufkomd.apps.googleusercontent.com",
          "client_type": 3
        }
      ],
      "api_key": [
        {
          "current_key": "AIzaSyCmLFTmCTPybqj5ttVpvDkkwcLDoPcwuI0"
        }
      ],
      "services": {
        "appinvite_service": {
          "other_platform_oauth_client": [
            {
              "client_id": "854865861013-as04qpfc2r78ntdd3hg23bqnviufkomd.apps.googleusercontent.com",
              "client_type": 3
            },
            {
              "client_id": "854865861013-p42of19a4gqslmocm7dv483uqkqgu1fu.apps.googleusercontent.com",
              "client_type": 2,
              "ios_info": {
                "bundle_id": "com.getmoneytree.sdk.MyAwesomeApp"
              }
            }
          ]
        }
      }
    },
    {
      "client_info": {
        "mobilesdk_app_id": "1:854865861013:android:2cd01195c7cb594bf97e9c",
        "android_client_info": {
          "package_name": "com.getmoneytree.sample.awesomeapp.development"
        }
      },
      "oauth_client": [
        {
          "client_id": "854865861013-vn0v655thbkih7579an5eh70mtbdnu0v.apps.googleusercontent.com",
          "client_type": 1,
          "android_info": {
            "package_name": "com.getmoneytree.sample.awesomeapp.development",
            "certificate_hash": "564f29ebeffd514305fb8a3f673b650bcb6dabe9"
          }
        },
        {
          "client_id": "854865861013-as04qpfc2r78ntdd3hg23bqnviufkomd.apps.googleusercontent.com",
          "client_type": 3
        }
      ],
      "api_key": [
        {
          "current_key": "AIzaSyCmLFTmCTPybqj5ttVpvDkkwcLDoPcwuI0"
        }
      ],
      "services": {
        "appinvite_service": {
          "other_platform_oauth_client": [
            {
              "client_id": "854865861013-as04qpfc2r78ntdd3hg23bqnviufkomd.apps.googleusercontent.com",
              "client_type": 3
            },
            {
              "client_id": "854865861013-p42of19a4gqslmocm7dv483uqkqgu1fu.apps.googleusercontent.com",
              "client_type": 2,
              "ios_info": {
                "bundle_id": "com.getmoneytree.sdk.MyAwesomeApp"
              }
            }
          ]
        }
      }
    },
    {
      "client_info": {
        "mobilesdk_app_id": "1:854865861013:android:bf691f91d40544bdf97e9c",
        "android_client_info": {
          "package_name": "com.getmoneytree.sample.awesomeapp.staging"
        }
      },
      "oauth_client": [
        {
          "client_id": "854865861013-8e2sim01t5cm4egs31j0kj9ula9qjijc.apps.googleusercontent.com",
          "client_type": 1,
          "android_info": {
            "package_name": "com.getmoneytree.sample.awesomeapp.staging",
            "certificate_hash": "564f29ebeffd514305fb8a3f673b650bcb6dabe9"
          }
        },
        {
          "client_id": "854865861013-as04qpfc2r78ntdd3hg23bqnviufkomd.apps.googleusercontent.com",
          "client_type": 3
        }
      ],
      "api_key": [
        {
          "current_key": "AIzaSyCmLFTmCTPybqj5ttVpvDkkwcLDoPcwuI0"
        }
      ],
      "services": {
        "appinvite_service": {
          "other_platform_oauth_client": [
            {
              "client_id": "854865861013-as04qpfc2r78ntdd3hg23bqnviufkomd.apps.googleusercontent.com",
              "client_type": 3
            },
            {
              "client_id": "854865861013-p42of19a4gqslmocm7dv483uqkqgu1fu.apps.googleusercontent.com",
              "client_type": 2,
              "ios_info": {
                "bundle_id": "com.getmoneytree.sdk.MyAwesomeApp"
              }
            }
          ]
        }
      }
    }
  ],
  "configuration_version": "1"
}